tennga/__init__.py
tennga/__main__.py
tennga/srcmake.py
tennga/tennga.py
tennga-1.2.4.dist-info/LICENSE
tennga-1.2.4.dist-info/METADATA
tennga-1.2.4.dist-info/WHEEL
tennga-1.2.4.dist-info/top_level.txt
tennga-1.2.4.dist-info/RECORD
