Metadata-Version: 2.1
Name: tennga
Version: 1.2.4
Summary: 一个实现简易,使用简易的源管理器
Home-page: https://github.com/shinoairisu/tennga
Author: 肥希的肥猫
Author-email: 281001460@qq.com
License: UNKNOWN
Platform: UNKNOWN
Classifier: Programming Language :: Python :: 3
Classifier: License :: OSI Approved :: MIT License
Classifier: Operating System :: MacOS
Classifier: Operating System :: Microsoft
Classifier: Operating System :: POSIX
Classifier: Operating System :: Unix
Requires-Python: >=3
License-File: LICENSE
Requires-Dist: requests
